{"userProfileId": 100909212, "totalKilocalories": 3275.0, "activeKilocalories": 925.0, "bmrKilocalories": 2350.0, "wellnessKilocalories": 3275.0, "burnedKilocalories": null, "consumedKilocalories": null, "remainingKilocalories": 2595.0, "totalSteps": 10991, "netCalorieGoal": 1670, "totalDistanceMeters": 10302, "wellnessDistanceMeters": 10302, "wellnessActiveKilocalories": 925.0, "netRemainingKilocalories": 2595.0, "userDailySummaryId": 100909212, "calendarDate": "2025-09-11", "rule": {"typeId": 2, "typeKey": "private"}, "uuid": "71ef47bcca204d3b9da6d4bdc54c825e", "dailyStepGoal": 6170, "wellnessStartTimeGmt": "2025-09-11T06:00:00.0", "wellnessStartTimeLocal": "2025-09-11T00:00:00.0", "wellnessEndTimeGmt": "2025-09-12T06:00:00.0", "wellnessEndTimeLocal": "2025-09-12T00:00:00.0", "durationInMilliseconds": 86400000, "wellnessDescription": null, "highlyActiveSeconds": 2836, "activeSeconds": 7607, "sedentarySeconds": 75957, "sleepingSeconds": 0, "includesWellnessData": true, "includesActivityData": true, "includesCalorieConsumedData": false, "privacyProtected": false, "moderateIntensityMinutes": 13, "vigorousIntensityMinutes": 30, "floorsAscendedInMeters": null, "floorsDescendedInMeters": null, "floorsAscended": null, "floorsDescended": null, "intensityMinutesGoal": 150, "userFloorsAscendedGoal": 10, "minHeartRate": 64, "maxHeartRate": 184, "restingHeartRate": 70, "lastSevenDaysAvgRestingHeartRate": 67, "source": "GARMIN", "averageStressLevel": 66, "maxStressLevel": 98, "stressDuration": 37140, "restStressDuration": 1140, "activityStressDuration": 16320, "uncategorizedStressDuration": 31200, "totalStressDuration": 85800, "lowStressDuration": 6240, "mediumStressDuration": 18120, "highStressDuration": 12780, "stressPercentage": 43.29, "restStressPercentage": 1.33, "activityStressPercentage": 19.02, "uncategorizedStressPercentage": 36.36, "lowStressPercentage": 7.27, "mediumStressPercentage": 21.12, "highStressPercentage": 14.9, "stressQualifier": "VERY_STRESSFUL_AWAKE", "measurableAwakeDuration": 53520, "measurableAsleepDuration": 1080, "lastSyncTimestampGMT": null, "minAvgHeartRate": 67, "maxAvgHeartRate": 183, "bodyBatteryChargedValue": 0, "bodyBatteryDrainedValue": 62, "bodyBatteryHighestValue": 67, "bodyBatteryLowestValue": 5, "bodyBatteryMostRecentValue": 5, "bodyBatteryDuringSleep": null, "bodyBatteryAtWakeTime": null, "bodyBatteryVersion": 2.0, "abnormalHeartRateAlertsCount": null, "averageSpo2": 93.0, "lowestSpo2": 89, "latestSpo2": 90, "latestSpo2ReadingTimeGmt": "2025-09-12T06:00:00.0", "latestSpo2ReadingTimeLocal": "2025-09-12T00:00:00.0", "averageMonitoringEnvironmentAltitude": null, "restingCaloriesFromActivity": 47.0, "avgWakingRespirationValue": 14.0, "highestRespirationValue": 21.0, "lowestRespirationValue": 6.0, "latestRespirationValue": 11.0, "latestRespirationTimeGMT": "2025-09-12T06:00:00.0", "respirationAlgorithmVersion": 100}