{"userProfileId": 100909212, "totalKilocalories": 3120.0, "activeKilocalories": 802.0, "bmrKilocalories": 2318.0, "wellnessKilocalories": 3120.0, "burnedKilocalories": null, "consumedKilocalories": null, "remainingKilocalories": null, "totalSteps": 5935, "netCalorieGoal": null, "totalDistanceMeters": 5602, "wellnessDistanceMeters": 5602, "wellnessActiveKilocalories": 802.0, "netRemainingKilocalories": 802.0, "userDailySummaryId": 100909212, "calendarDate": "2025-07-08", "rule": {"typeId": 2, "typeKey": "private"}, "uuid": "d444af3754804dd8bfff339fbf3b7e8a", "dailyStepGoal": 8850, "wellnessStartTimeGmt": "2025-07-08T06:00:00.0", "wellnessStartTimeLocal": "2025-07-08T00:00:00.0", "wellnessEndTimeGmt": "2025-07-09T06:00:00.0", "wellnessEndTimeLocal": "2025-07-09T00:00:00.0", "durationInMilliseconds": 86400000, "wellnessDescription": null, "highlyActiveSeconds": 2799, "activeSeconds": 3540, "sedentarySeconds": 80061, "sleepingSeconds": 0, "includesWellnessData": true, "includesActivityData": true, "includesCalorieConsumedData": false, "privacyProtected": false, "moderateIntensityMinutes": 39, "vigorousIntensityMinutes": 31, "floorsAscendedInMeters": null, "floorsDescendedInMeters": null, "floorsAscended": null, "floorsDescended": null, "intensityMinutesGoal": 150, "userFloorsAscendedGoal": 10, "minHeartRate": 61, "maxHeartRate": 188, "restingHeartRate": 63, "lastSevenDaysAvgRestingHeartRate": 59, "source": "GARMIN", "averageStressLevel": 59, "maxStressLevel": 99, "stressDuration": 11340, "restStressDuration": 1620, "activityStressDuration": 5880, "uncategorizedStressDuration": 67440, "totalStressDuration": 86280, "lowStressDuration": 3000, "mediumStressDuration": 4800, "highStressDuration": 3540, "stressPercentage": 13.14, "restStressPercentage": 1.88, "activityStressPercentage": 6.82, "uncategorizedStressPercentage": 78.16, "lowStressPercentage": 3.48, "mediumStressPercentage": 5.56, "highStressPercentage": 4.1, "stressQualifier": "UNKNOWN", "measurableAwakeDuration": 18360, "measurableAsleepDuration": 480, "lastSyncTimestampGMT": null, "minAvgHeartRate": 63, "maxAvgHeartRate": 186, "bodyBatteryChargedValue": 0, "bodyBatteryDrainedValue": 26, "bodyBatteryHighestValue": 31, "bodyBatteryLowestValue": 5, "bodyBatteryMostRecentValue": 5, "bodyBatteryDuringSleep": null, "bodyBatteryAtWakeTime": null, "bodyBatteryVersion": 2.0, "abnormalHeartRateAlertsCount": null, "averageSpo2": 95.0, "lowestSpo2": 88, "latestSpo2": 93, "latestSpo2ReadingTimeGmt": "2025-07-09T06:00:00.0", "latestSpo2ReadingTimeLocal": "2025-07-09T00:00:00.0", "averageMonitoringEnvironmentAltitude": null, "restingCaloriesFromActivity": 28.0, "avgWakingRespirationValue": 14.0, "highestRespirationValue": 16.0, "lowestRespirationValue": 11.0, "latestRespirationValue": 11.0, "latestRespirationTimeGMT": "2025-07-09T06:00:00.0", "respirationAlgorithmVersion": 100}