{"userProfileId": 100909212, "totalKilocalories": 2909.0, "activeKilocalories": 559.0, "bmrKilocalories": 2350.0, "wellnessKilocalories": 2909.0, "burnedKilocalories": null, "consumedKilocalories": null, "remainingKilocalories": 2229.0, "totalSteps": 4728, "netCalorieGoal": 1670, "totalDistanceMeters": 4626, "wellnessDistanceMeters": 4626, "wellnessActiveKilocalories": 559.0, "netRemainingKilocalories": 2229.0, "userDailySummaryId": 100909212, "calendarDate": "2025-09-09", "rule": {"typeId": 2, "typeKey": "private"}, "uuid": "fc22f2158081460a9badf225fee7f253", "dailyStepGoal": 7210, "wellnessStartTimeGmt": "2025-09-09T06:00:00.0", "wellnessStartTimeLocal": "2025-09-09T00:00:00.0", "wellnessEndTimeGmt": "2025-09-10T06:00:00.0", "wellnessEndTimeLocal": "2025-09-10T00:00:00.0", "durationInMilliseconds": 86400000, "wellnessDescription": null, "highlyActiveSeconds": 2079, "activeSeconds": 1330, "sedentarySeconds": 76751, "sleepingSeconds": 6240, "includesWellnessData": true, "includesActivityData": true, "includesCalorieConsumedData": false, "privacyProtected": false, "moderateIntensityMinutes": 23, "vigorousIntensityMinutes": 27, "floorsAscendedInMeters": null, "floorsDescendedInMeters": null, "floorsAscended": null, "floorsDescended": null, "intensityMinutesGoal": 150, "userFloorsAscendedGoal": 10, "minHeartRate": 70, "maxHeartRate": 145, "restingHeartRate": 72, "lastSevenDaysAvgRestingHeartRate": 72, "source": "GARMIN", "averageStressLevel": 62, "maxStressLevel": 99, "stressDuration": 7080, "restStressDuration": 600, "activityStressDuration": 4080, "uncategorizedStressDuration": 74160, "totalStressDuration": 85920, "lowStressDuration": 1080, "mediumStressDuration": 4560, "highStressDuration": 1440, "stressPercentage": 8.24, "restStressPercentage": 0.7, "activityStressPercentage": 4.75, "uncategorizedStressPercentage": 86.31, "lowStressPercentage": 1.26, "mediumStressPercentage": 5.31, "highStressPercentage": 1.68, "stressQualifier": "UNKNOWN", "measurableAwakeDuration": 5280, "measurableAsleepDuration": 6480, "lastSyncTimestampGMT": null, "minAvgHeartRate": 71, "maxAvgHeartRate": 143, "bodyBatteryChargedValue": 3, "bodyBatteryDrainedValue": 19, "bodyBatteryHighestValue": 24, "bodyBatteryLowestValue": 5, "bodyBatteryMostRecentValue": 8, "bodyBatteryDuringSleep": null, "bodyBatteryAtWakeTime": null, "bodyBatteryVersion": 2.0, "abnormalHeartRateAlertsCount": null, "averageSpo2": 87.0, "lowestSpo2": 79, "latestSpo2": 87, "latestSpo2ReadingTimeGmt": "2025-09-10T06:00:00.0", "latestSpo2ReadingTimeLocal": "2025-09-10T00:00:00.0", "averageMonitoringEnvironmentAltitude": null, "restingCaloriesFromActivity": 41.0, "avgWakingRespirationValue": 14.0, "highestRespirationValue": 19.0, "lowestRespirationValue": 10.0, "latestRespirationValue": 10.0, "latestRespirationTimeGMT": "2025-09-10T06:00:00.0", "respirationAlgorithmVersion": 100}