{"userProfileId": 100909212, "totalKilocalories": 2513.0, "activeKilocalories": 304.0, "bmrKilocalories": 2209.0, "wellnessKilocalories": 2513.0, "burnedKilocalories": null, "consumedKilocalories": null, "remainingKilocalories": 2513.0, "totalSteps": 4452, "netCalorieGoal": null, "totalDistanceMeters": 3622, "wellnessDistanceMeters": 3622, "wellnessActiveKilocalories": 304.0, "netRemainingKilocalories": 304.0, "userDailySummaryId": 100909212, "calendarDate": "2022-07-24", "rule": {"typeId": 2, "typeKey": "private"}, "uuid": "7a8c0a10ba6240d5bc4432f39b64d50c", "dailyStepGoal": 6880, "wellnessStartTimeGmt": "2022-07-24T06:00:00.0", "wellnessStartTimeLocal": "2022-07-24T00:00:00.0", "wellnessEndTimeGmt": "2022-07-25T06:00:00.0", "wellnessEndTimeLocal": "2022-07-25T00:00:00.0", "durationInMilliseconds": 86400000, "wellnessDescription": null, "highlyActiveSeconds": 1160, "activeSeconds": 5290, "sedentarySeconds": 52170, "sleepingSeconds": 27780, "includesWellnessData": true, "includesActivityData": false, "includesCalorieConsumedData": false, "privacyProtected": false, "moderateIntensityMinutes": 0, "vigorousIntensityMinutes": 0, "floorsAscendedInMeters": null, "floorsDescendedInMeters": null, "floorsAscended": null, "floorsDescended": null, "intensityMinutesGoal": 150, "userFloorsAscendedGoal": 10, "minHeartRate": 49, "maxHeartRate": 118, "restingHeartRate": 54, "lastSevenDaysAvgRestingHeartRate": 50, "source": "GARMIN", "averageStressLevel": 51, "maxStressLevel": 96, "stressDuration": 56280, "restStressDuration": 19980, "activityStressDuration": 9300, "uncategorizedStressDuration": 720, "totalStressDuration": 86280, "lowStressDuration": 19740, "mediumStressDuration": 13320, "highStressDuration": 23220, "stressPercentage": 65.23, "restStressPercentage": 23.16, "activityStressPercentage": 10.78, "uncategorizedStressPercentage": 0.83, "lowStressPercentage": 22.88, "mediumStressPercentage": 15.44, "highStressPercentage": 26.91, "stressQualifier": "STRESSFUL", "measurableAwakeDuration": 59100, "measurableAsleepDuration": 26460, "lastSyncTimestampGMT": null, "minAvgHeartRate": 51, "maxAvgHeartRate": 112, "bodyBatteryChargedValue": 31, "bodyBatteryDrainedValue": 15, "bodyBatteryHighestValue": 21, "bodyBatteryLowestValue": 5, "bodyBatteryMostRecentValue": 21, "bodyBatteryDuringSleep": null, "bodyBatteryAtWakeTime": null, "bodyBatteryVersion": 2.0, "abnormalHeartRateAlertsCount": null, "averageSpo2": null, "lowestSpo2": null, "latestSpo2": null, "latestSpo2ReadingTimeGmt": null, "latestSpo2ReadingTimeLocal": null, "averageMonitoringEnvironmentAltitude": null, "restingCaloriesFromActivity": null, "avgWakingRespirationValue": 14.0, "highestRespirationValue": 26.0, "lowestRespirationValue": 10.0, "latestRespirationValue": 14.0, "latestRespirationTimeGMT": "2022-07-25T06:00:00.0"}