{"userProfileId": 100909212, "totalKilocalories": 2252.0, "activeKilocalories": 43.0, "bmrKilocalories": 2209.0, "wellnessKilocalories": 2252.0, "burnedKilocalories": null, "consumedKilocalories": null, "remainingKilocalories": 2252.0, "totalSteps": 1546, "netCalorieGoal": null, "totalDistanceMeters": 1252, "wellnessDistanceMeters": 1252, "wellnessActiveKilocalories": 43.0, "netRemainingKilocalories": 43.0, "userDailySummaryId": 100909212, "calendarDate": "2022-09-14", "rule": {"typeId": 2, "typeKey": "private"}, "uuid": "965dcfadea31480483fbf7f74e47ed0b", "dailyStepGoal": 6560, "wellnessStartTimeGmt": "2022-09-14T04:00:00.0", "wellnessStartTimeLocal": "2022-09-14T00:00:00.0", "wellnessEndTimeGmt": "2022-09-15T04:00:00.0", "wellnessEndTimeLocal": "2022-09-15T00:00:00.0", "durationInMilliseconds": 86400000, "wellnessDescription": null, "highlyActiveSeconds": 580, "activeSeconds": 1305, "sedentarySeconds": 44735, "sleepingSeconds": 39780, "includesWellnessData": true, "includesActivityData": false, "includesCalorieConsumedData": false, "privacyProtected": false, "moderateIntensityMinutes": 0, "vigorousIntensityMinutes": 0, "floorsAscendedInMeters": null, "floorsDescendedInMeters": null, "floorsAscended": null, "floorsDescended": null, "intensityMinutesGoal": 150, "userFloorsAscendedGoal": 10, "minHeartRate": 49, "maxHeartRate": 102, "restingHeartRate": 54, "lastSevenDaysAvgRestingHeartRate": 51, "source": "GARMIN", "averageStressLevel": 27, "maxStressLevel": 96, "stressDuration": 34440, "restStressDuration": 47760, "activityStressDuration": 3180, "uncategorizedStressDuration": 540, "totalStressDuration": 85920, "lowStressDuration": 28380, "mediumStressDuration": 4800, "highStressDuration": 1260, "stressPercentage": 40.08, "restStressPercentage": 55.59, "activityStressPercentage": 3.7, "uncategorizedStressPercentage": 0.63, "lowStressPercentage": 33.03, "mediumStressPercentage": 5.59, "highStressPercentage": 1.47, "stressQualifier": "BALANCED", "measurableAwakeDuration": 48960, "measurableAsleepDuration": 36420, "lastSyncTimestampGMT": null, "minAvgHeartRate": 50, "maxAvgHeartRate": 99, "bodyBatteryChargedValue": 70, "bodyBatteryDrainedValue": 33, "bodyBatteryHighestValue": 63, "bodyBatteryLowestValue": 8, "bodyBatteryMostRecentValue": 45, "bodyBatteryDuringSleep": null, "bodyBatteryAtWakeTime": null, "bodyBatteryVersion": 2.0, "abnormalHeartRateAlertsCount": null, "averageSpo2": null, "lowestSpo2": null, "latestSpo2": null, "latestSpo2ReadingTimeGmt": null, "latestSpo2ReadingTimeLocal": null, "averageMonitoringEnvironmentAltitude": null, "restingCaloriesFromActivity": null, "avgWakingRespirationValue": 14.0, "highestRespirationValue": 18.0, "lowestRespirationValue": 9.0, "latestRespirationValue": 9.0, "latestRespirationTimeGMT": "2022-09-15T04:00:00.0"}