{"userProfileId": 100909212, "totalKilocalories": 2748.0, "activeKilocalories": 539.0, "bmrKilocalories": 2209.0, "wellnessKilocalories": 2748.0, "burnedKilocalories": null, "consumedKilocalories": null, "remainingKilocalories": 2748.0, "totalSteps": 6321, "netCalorieGoal": null, "totalDistanceMeters": 6848, "wellnessDistanceMeters": 6848, "wellnessActiveKilocalories": 539.0, "netRemainingKilocalories": 539.0, "userDailySummaryId": 100909212, "calendarDate": "2022-09-26", "rule": {"typeId": 2, "typeKey": "private"}, "uuid": "f957180480734c9abdf1384b6f66e504", "dailyStepGoal": 5340, "wellnessStartTimeGmt": "2022-09-26T04:00:00.0", "wellnessStartTimeLocal": "2022-09-26T00:00:00.0", "wellnessEndTimeGmt": "2022-09-27T04:00:00.0", "wellnessEndTimeLocal": "2022-09-27T00:00:00.0", "durationInMilliseconds": 86400000, "wellnessDescription": null, "highlyActiveSeconds": 2453, "activeSeconds": 2691, "sedentarySeconds": 75016, "sleepingSeconds": 6240, "includesWellnessData": true, "includesActivityData": true, "includesCalorieConsumedData": false, "privacyProtected": false, "moderateIntensityMinutes": 6, "vigorousIntensityMinutes": 26, "floorsAscendedInMeters": null, "floorsDescendedInMeters": null, "floorsAscended": null, "floorsDescended": null, "intensityMinutesGoal": 150, "userFloorsAscendedGoal": 10, "minHeartRate": 55, "maxHeartRate": 176, "restingHeartRate": 53, "lastSevenDaysAvgRestingHeartRate": 49, "source": "GARMIN", "averageStressLevel": 59, "maxStressLevel": 99, "stressDuration": 14640, "restStressDuration": 6000, "activityStressDuration": 4860, "uncategorizedStressDuration": 3540, "totalStressDuration": 29040, "lowStressDuration": 960, "mediumStressDuration": 4860, "highStressDuration": 8820, "stressPercentage": 50.41, "restStressPercentage": 20.66, "activityStressPercentage": 16.74, "uncategorizedStressPercentage": 12.19, "lowStressPercentage": 3.31, "mediumStressPercentage": 16.74, "highStressPercentage": 30.37, "stressQualifier": "UNKNOWN", "measurableAwakeDuration": 25500, "measurableAsleepDuration": 0, "lastSyncTimestampGMT": null, "minAvgHeartRate": 56, "maxAvgHeartRate": 175, "bodyBatteryChargedValue": 7, "bodyBatteryDrainedValue": 28, "bodyBatteryHighestValue": 33, "bodyBatteryLowestValue": 5, "bodyBatteryMostRecentValue": 12, "bodyBatteryDuringSleep": null, "bodyBatteryAtWakeTime": null, "bodyBatteryVersion": 2.0, "abnormalHeartRateAlertsCount": null, "averageSpo2": null, "lowestSpo2": null, "latestSpo2": null, "latestSpo2ReadingTimeGmt": null, "latestSpo2ReadingTimeLocal": null, "averageMonitoringEnvironmentAltitude": null, "restingCaloriesFromActivity": 40.0, "avgWakingRespirationValue": 13.0, "highestRespirationValue": 19.0, "lowestRespirationValue": 10.0, "latestRespirationValue": 15.0, "latestRespirationTimeGMT": "2022-09-27T04:00:00.0"}