{"activityId": 17183813890, "activityName": "Edgewood Running", "startTimeLocal": "2024-10-02 07:31:52", "startTimeGMT": "2024-10-02 11:31:52", "activityType": {"typeId": 1, "typeKey": "running", "parentTypeId": 17, "isHidden": false, "restricted": false, "trimmable": true}, "eventType": {"typeId": 9, "typeKey": "uncategorized", "sortOrder": 10}, "distance": 3471.1201171875, "duration": 1357.8060302734375, "elapsedDuration": 1357.8060302734375, "movingDuration": 1357.0, "elevationGain": 49.198760986328125, "elevationLoss": 62.53178405761719, "averageSpeed": 2.555999994277954, "maxSpeed": 3.3959999084472656, "startLatitude": 40.43330571614206, "startLongitude": -79.88689234480262, "hasPolyline": true, "hasImages": false, "ownerId": 100909212, "ownerDisplayName": "f81a06f2-a406-4ac5-8551-f05a737db9b4", "ownerFullName": "Max", "ownerProfileImageUrlSmall": "https://s3.amazonaws.com/garmin-connect-prod/profile_images/1bc372d7-fd97-4436-a7d4-1f4b5262f029-100909212.png", "ownerProfileImageUrlMedium": "https://s3.amazonaws.com/garmin-connect-prod/profile_images/d043f117-8262-4324-815a-2f4c2f560f4a-100909212.png", "ownerProfileImageUrlLarge": "https://s3.amazonaws.com/garmin-connect-prod/profile_images/1cafae13-0318-4c15-b882-7f24581e2149-100909212.png", "calories": 290.0, "bmrCalories": 35.0, "averageHR": 160.0, "maxHR": 184.0, "averageRunningCadenceInStepsPerMinute": 144.59375, "maxRunningCadenceInStepsPerMinute": 154.0, "steps": 3278, "userRoles": ["SCOPE_GOLF_API_READ", "SCOPE_DI_OAUTH_2_CREATE_DI_USER", "SCOPE_ATP_READ", "SCOPE_DIVE_API_WRITE", "SCOPE_COMMUNITY_COURSE_ADMIN_READ", "SCOPE_DIVE_API_READ", "SCOPE_DI_OAUTH_2_CLIENT_READ", "SCOPE_CONNECT_WRITE", "SCOPE_COMMUNITY_COURSE_WRITE", "SCOPE_CONNECT_MCT_DAILY_LOG_READ", "SCOPE_MESSAGE_GENERATION_READ", "SCOPE_DI_OAUTH_2_CLIENT_REVOCATION_ADMIN", "SCOPE_CONNECT_WEB_TEMPLATE_RENDER", "SCOPE_OMT_SUBSCRIPTION_ADMIN_READ", "SCOPE_DI_OAUTH_2_MANAGED_STATUS_ADMIN_WRITE", "SCOPE_CONNECT_NON_SOCIAL_SHARED_READ", "SCOPE_CONNECT_READ", "SCOPE_DI_OAUTH_2_PRERELEASE_PERMISSIONS_ADMIN_WRITE", "SCOPE_SCOPE_DI_OAUTH_2_CREATE_DI_USER", "SCOPE_DI_OAUTH_2_TOKEN_ADMIN", "ROLE_CONNECTUSER", "ROLE_FITNESS_USER", "ROLE_WELLNESS_USER"], "privacy": {"typeId": 2, "typeKey": "private"}, "userPro": false, "hasVideo": false, "timeZoneId": 149, "beginTimestamp": 1727868712000, "sportTypeId": 1, "aerobicTrainingEffect": 4.699999809265137, "anaerobicTrainingEffect": 2.0, "avgStrideLength": 106.1180272097075, "vO2MaxValue": 39.0, "deviceId": 3394455214, "minElevation": 235.0, "maxElevation": 276.0, "maxDoubleCadence": 154.0, "summarizedDiveInfo": {"summarizedDiveGases": []}, "maxVerticalSpeed": 0.7708180745442709, "manufacturer": "GARMIN", "locationName": "Edgewood", "lapCount": 3, "endLatitude": 40.43303648941219, "endLongitude": -79.8990404047072, "waterEstimated": 135.0, "minActivityLapDuration": 99.12200164794922, "aerobicTrainingEffectMessage": "HIGHLY_IMPROVING_VO2_MAX_16", "anaerobicTrainingEffectMessage": "MAINTAINING_ANAEROBIC_BASE_1", "splitSummaries": [{"noOfSplits": 1, "totalAscent": 181.10999999940395, "duration": 1357.7669677734375, "splitType": "RWD_RUN", "numClimbSends": 0, "maxElevationGain": 181.10999999940395, "averageElevationGain": 181.10999999940395, "maxDistance": 3471, "distance": 3471.1201171875, "averageSpeed": 2.555999994277954, "maxSpeed": 3.3959999084472656, "numFalls": 0, "elevationLoss": 113.62999999523163}], "hasSplits": true, "moderateIntensityMinutes": 1, "vigorousIntensityMinutes": 21, "hasHeatMap": false, "fastestSplit_1000": 368.9750061035156, "fastestSplit_1609": 589.781982421875, "endTimeGMT": "2024-10-02 11:54:29", "qualifyingDive": false, "pr": false, "purposeful": false, "manualActivity": false, "autoCalcCalories": false, "elevationCorrected": true, "atpActivity": false, "favorite": false, "decoDive": false, "parent": false}