{"userProfileId": 100909212, "totalKilocalories": 2200.0, "activeKilocalories": 89.0, "bmrKilocalories": 2111.0, "wellnessKilocalories": 2200.0, "burnedKilocalories": null, "consumedKilocalories": null, "remainingKilocalories": 2200.0, "totalSteps": 2039, "netCalorieGoal": null, "totalDistanceMeters": 1681, "wellnessDistanceMeters": 1681, "wellnessActiveKilocalories": 89.0, "netRemainingKilocalories": 89.0, "userDailySummaryId": 100909212, "calendarDate": "2023-07-09", "rule": {"typeId": 2, "typeKey": "private"}, "uuid": "992c439ba053478aba6984ae69e54ffb", "dailyStepGoal": 5020, "wellnessStartTimeGmt": "2023-07-09T05:00:00.0", "wellnessStartTimeLocal": "2023-07-09T00:00:00.0", "wellnessEndTimeGmt": "2023-07-10T04:00:00.0", "wellnessEndTimeLocal": "2023-07-10T00:00:00.0", "durationInMilliseconds": 82800000, "wellnessDescription": null, "highlyActiveSeconds": 880, "activeSeconds": 3550, "sedentarySeconds": 68230, "sleepingSeconds": 10140, "includesWellnessData": true, "includesActivityData": false, "includesCalorieConsumedData": false, "privacyProtected": false, "moderateIntensityMinutes": 0, "vigorousIntensityMinutes": 0, "floorsAscendedInMeters": null, "floorsDescendedInMeters": null, "floorsAscended": null, "floorsDescended": null, "intensityMinutesGoal": 150, "userFloorsAscendedGoal": 10, "minHeartRate": 51, "maxHeartRate": 100, "restingHeartRate": 53, "lastSevenDaysAvgRestingHeartRate": 51, "source": "GARMIN", "averageStressLevel": 46, "maxStressLevel": 94, "stressDuration": 22080, "restStressDuration": 7380, "activityStressDuration": 5460, "uncategorizedStressDuration": null, "totalStressDuration": 34920, "lowStressDuration": 8400, "mediumStressDuration": 9360, "highStressDuration": 4320, "stressPercentage": 63.23, "restStressPercentage": 21.13, "activityStressPercentage": 15.64, "uncategorizedStressPercentage": 0.0, "lowStressPercentage": 24.05, "mediumStressPercentage": 26.8, "highStressPercentage": 12.37, "stressQualifier": "STRESSFUL_AWAKE", "measurableAwakeDuration": 30060, "measurableAsleepDuration": 4860, "lastSyncTimestampGMT": null, "minAvgHeartRate": 52, "maxAvgHeartRate": 99, "bodyBatteryChargedValue": 9, "bodyBatteryDrainedValue": 16, "bodyBatteryHighestValue": 21, "bodyBatteryLowestValue": 5, "bodyBatteryMostRecentValue": 14, "bodyBatteryDuringSleep": null, "bodyBatteryAtWakeTime": null, "bodyBatteryVersion": 2.0, "abnormalHeartRateAlertsCount": null, "averageSpo2": 93.0, "lowestSpo2": 86, "latestSpo2": 92, "latestSpo2ReadingTimeGmt": "2023-07-10T04:00:00.0", "latestSpo2ReadingTimeLocal": "2023-07-09T23:00:00.0", "averageMonitoringEnvironmentAltitude": null, "restingCaloriesFromActivity": null, "avgWakingRespirationValue": 14.0, "highestRespirationValue": 17.0, "lowestRespirationValue": 10.0, "latestRespirationValue": 11.0, "latestRespirationTimeGMT": "2023-07-10T04:00:00.0"}