{"userProfileId": 100909212, "totalKilocalories": 2713.0, "activeKilocalories": 510.0, "bmrKilocalories": 2203.0, "wellnessKilocalories": 2713.0, "burnedKilocalories": null, "consumedKilocalories": null, "remainingKilocalories": 2713.0, "totalSteps": 5163, "netCalorieGoal": null, "totalDistanceMeters": 4266, "wellnessDistanceMeters": 4266, "wellnessActiveKilocalories": 510.0, "netRemainingKilocalories": 510.0, "userDailySummaryId": 100909212, "calendarDate": "2023-04-16", "rule": {"typeId": 2, "typeKey": "private"}, "uuid": "596f0be0ad4a4dcba29384b496ab0be7", "dailyStepGoal": 5180, "wellnessStartTimeGmt": "2023-04-16T04:00:00.0", "wellnessStartTimeLocal": "2023-04-16T00:00:00.0", "wellnessEndTimeGmt": "2023-04-17T04:00:00.0", "wellnessEndTimeLocal": "2023-04-17T00:00:00.0", "durationInMilliseconds": 86400000, "wellnessDescription": null, "highlyActiveSeconds": 3381, "activeSeconds": 3984, "sedentarySeconds": 43575, "sleepingSeconds": 35460, "includesWellnessData": true, "includesActivityData": false, "includesCalorieConsumedData": false, "privacyProtected": false, "moderateIntensityMinutes": 0, "vigorousIntensityMinutes": 0, "floorsAscendedInMeters": null, "floorsDescendedInMeters": null, "floorsAscended": null, "floorsDescended": null, "intensityMinutesGoal": 150, "userFloorsAscendedGoal": 10, "minHeartRate": 46, "maxHeartRate": 126, "restingHeartRate": 55, "lastSevenDaysAvgRestingHeartRate": 54, "source": "GARMIN", "averageStressLevel": 37, "maxStressLevel": 99, "stressDuration": 36060, "restStressDuration": 41520, "activityStressDuration": 7860, "uncategorizedStressDuration": 780, "totalStressDuration": 86220, "lowStressDuration": 13200, "mediumStressDuration": 10020, "highStressDuration": 12840, "stressPercentage": 41.82, "restStressPercentage": 48.16, "activityStressPercentage": 9.12, "uncategorizedStressPercentage": 0.9, "lowStressPercentage": 15.31, "mediumStressPercentage": 11.62, "highStressPercentage": 14.89, "stressQualifier": "BALANCED", "measurableAwakeDuration": 53940, "measurableAsleepDuration": 31500, "lastSyncTimestampGMT": null, "minAvgHeartRate": 47, "maxAvgHeartRate": 125, "bodyBatteryChargedValue": 68, "bodyBatteryDrainedValue": 53, "bodyBatteryHighestValue": 65, "bodyBatteryLowestValue": 5, "bodyBatteryMostRecentValue": 20, "bodyBatteryDuringSleep": null, "bodyBatteryAtWakeTime": null, "bodyBatteryVersion": 2.0, "abnormalHeartRateAlertsCount": null, "averageSpo2": 90.0, "lowestSpo2": 74, "latestSpo2": 87, "latestSpo2ReadingTimeGmt": "2023-04-17T03:57:00.0", "latestSpo2ReadingTimeLocal": "2023-04-16T23:57:00.0", "averageMonitoringEnvironmentAltitude": null, "restingCaloriesFromActivity": null, "avgWakingRespirationValue": 13.0, "highestRespirationValue": 21.0, "lowestRespirationValue": 9.0, "latestRespirationValue": 12.0, "latestRespirationTimeGMT": "2023-04-17T03:56:00.0"}