{"userProfileId": 100909212, "totalKilocalories": 2813.0, "activeKilocalories": 553.0, "bmrKilocalories": 2260.0, "wellnessKilocalories": 2813.0, "burnedKilocalories": null, "consumedKilocalories": null, "remainingKilocalories": 2813.0, "totalSteps": 10832, "netCalorieGoal": null, "totalDistanceMeters": 9866, "wellnessDistanceMeters": 9866, "wellnessActiveKilocalories": 553.0, "netRemainingKilocalories": 553.0, "userDailySummaryId": 100909212, "calendarDate": "2023-07-19", "rule": {"typeId": 2, "typeKey": "private"}, "uuid": "2c824b2eb0f647f9a2ddb3e75c9d6bb0", "dailyStepGoal": 4930, "wellnessStartTimeGmt": "2023-07-19T04:00:00.0", "wellnessStartTimeLocal": "2023-07-19T00:00:00.0", "wellnessEndTimeGmt": "2023-07-20T04:00:00.0", "wellnessEndTimeLocal": "2023-07-20T00:00:00.0", "durationInMilliseconds": 86400000, "wellnessDescription": null, "highlyActiveSeconds": 2563, "activeSeconds": 6775, "sedentarySeconds": 47242, "sleepingSeconds": 29820, "includesWellnessData": true, "includesActivityData": true, "includesCalorieConsumedData": false, "privacyProtected": false, "moderateIntensityMinutes": 8, "vigorousIntensityMinutes": 19, "floorsAscendedInMeters": null, "floorsDescendedInMeters": null, "floorsAscended": null, "floorsDescended": null, "intensityMinutesGoal": 150, "userFloorsAscendedGoal": 10, "minHeartRate": 47, "maxHeartRate": 186, "restingHeartRate": 49, "lastSevenDaysAvgRestingHeartRate": 49, "source": "GARMIN", "averageStressLevel": 39, "maxStressLevel": 98, "stressDuration": 37620, "restStressDuration": 34980, "activityStressDuration": 10500, "uncategorizedStressDuration": 3120, "totalStressDuration": 86220, "lowStressDuration": 9840, "mediumStressDuration": 16020, "highStressDuration": 11760, "stressPercentage": 43.63, "restStressPercentage": 40.57, "activityStressPercentage": 12.18, "uncategorizedStressPercentage": 3.62, "lowStressPercentage": 11.41, "mediumStressPercentage": 18.58, "highStressPercentage": 13.64, "stressQualifier": "BALANCED", "measurableAwakeDuration": 52920, "measurableAsleepDuration": 30180, "lastSyncTimestampGMT": null, "minAvgHeartRate": 48, "maxAvgHeartRate": 186, "bodyBatteryChargedValue": 66, "bodyBatteryDrainedValue": 91, "bodyBatteryHighestValue": 100, "bodyBatteryLowestValue": 9, "bodyBatteryMostRecentValue": 20, "bodyBatteryDuringSleep": null, "bodyBatteryAtWakeTime": null, "bodyBatteryVersion": 2.0, "abnormalHeartRateAlertsCount": null, "averageSpo2": 91.0, "lowestSpo2": 83, "latestSpo2": 94, "latestSpo2ReadingTimeGmt": "2023-07-20T04:00:00.0", "latestSpo2ReadingTimeLocal": "2023-07-20T00:00:00.0", "averageMonitoringEnvironmentAltitude": null, "restingCaloriesFromActivity": 29.0, "avgWakingRespirationValue": 13.0, "highestRespirationValue": 18.0, "lowestRespirationValue": 8.0, "latestRespirationValue": 9.0, "latestRespirationTimeGMT": "2023-07-20T04:00:00.0"}