{"userProfileId": 100909212, "totalKilocalories": 2679.0, "activeKilocalories": 476.0, "bmrKilocalories": 2203.0, "wellnessKilocalories": 2679.0, "burnedKilocalories": null, "consumedKilocalories": null, "remainingKilocalories": 2679.0, "totalSteps": 5573, "netCalorieGoal": null, "totalDistanceMeters": 5653, "wellnessDistanceMeters": 5653, "wellnessActiveKilocalories": 476.0, "netRemainingKilocalories": 476.0, "userDailySummaryId": 100909212, "calendarDate": "2023-02-09", "rule": {"typeId": 2, "typeKey": "private"}, "uuid": "1e5c21efd07b4149aa77127ab9755c09", "dailyStepGoal": 3380, "wellnessStartTimeGmt": "2023-02-09T05:00:00.0", "wellnessStartTimeLocal": "2023-02-09T00:00:00.0", "wellnessEndTimeGmt": "2023-02-10T05:00:00.0", "wellnessEndTimeLocal": "2023-02-10T00:00:00.0", "durationInMilliseconds": 86400000, "wellnessDescription": null, "highlyActiveSeconds": 3049, "activeSeconds": 1904, "sedentarySeconds": 42687, "sleepingSeconds": 38760, "includesWellnessData": true, "includesActivityData": true, "includesCalorieConsumedData": false, "privacyProtected": false, "moderateIntensityMinutes": 8, "vigorousIntensityMinutes": 21, "floorsAscendedInMeters": null, "floorsDescendedInMeters": null, "floorsAscended": null, "floorsDescended": null, "intensityMinutesGoal": 150, "userFloorsAscendedGoal": 10, "minHeartRate": 48, "maxHeartRate": 187, "restingHeartRate": 50, "lastSevenDaysAvgRestingHeartRate": 55, "source": "GARMIN", "averageStressLevel": 26, "maxStressLevel": 98, "stressDuration": 22380, "restStressDuration": 53640, "activityStressDuration": 6000, "uncategorizedStressDuration": 3720, "totalStressDuration": 85740, "lowStressDuration": 7260, "mediumStressDuration": 11520, "highStressDuration": 3600, "stressPercentage": 26.1, "restStressPercentage": 62.56, "activityStressPercentage": 7.0, "uncategorizedStressPercentage": 4.34, "lowStressPercentage": 8.47, "mediumStressPercentage": 13.44, "highStressPercentage": 4.2, "stressQualifier": "BALANCED", "measurableAwakeDuration": 54060, "measurableAsleepDuration": 27960, "lastSyncTimestampGMT": null, "minAvgHeartRate": 49, "maxAvgHeartRate": 187, "bodyBatteryChargedValue": 93, "bodyBatteryDrainedValue": 76, "bodyBatteryHighestValue": 100, "bodyBatteryLowestValue": 24, "bodyBatteryMostRecentValue": 48, "bodyBatteryDuringSleep": null, "bodyBatteryAtWakeTime": null, "bodyBatteryVersion": 2.0, "abnormalHeartRateAlertsCount": null, "averageSpo2": 94.0, "lowestSpo2": 86, "latestSpo2": 94, "latestSpo2ReadingTimeGmt": "2023-02-10T04:59:00.0", "latestSpo2ReadingTimeLocal": "2023-02-09T23:59:00.0", "averageMonitoringEnvironmentAltitude": null, "restingCaloriesFromActivity": 28.0, "avgWakingRespirationValue": 13.0, "highestRespirationValue": 21.0, "lowestRespirationValue": 8.0, "latestRespirationValue": 13.0, "latestRespirationTimeGMT": "2023-02-10T05:00:00.0"}