{"userProfileId": 100909212, "totalKilocalories": 2788.0, "activeKilocalories": 464.0, "bmrKilocalories": 2324.0, "wellnessKilocalories": 2788.0, "burnedKilocalories": null, "consumedKilocalories": null, "remainingKilocalories": 2788.0, "totalSteps": 7863, "netCalorieGoal": null, "totalDistanceMeters": 6386, "wellnessDistanceMeters": 6386, "wellnessActiveKilocalories": 464.0, "netRemainingKilocalories": 464.0, "userDailySummaryId": 100909212, "calendarDate": "2024-12-30", "rule": {"typeId": 2, "typeKey": "private"}, "uuid": "8d3b5de5fbc545f08069ba816d9a792e", "dailyStepGoal": 7970, "wellnessStartTimeGmt": "2024-12-30T05:00:00.0", "wellnessStartTimeLocal": "2024-12-30T00:00:00.0", "wellnessEndTimeGmt": "2024-12-31T05:00:00.0", "wellnessEndTimeLocal": "2024-12-31T00:00:00.0", "durationInMilliseconds": 86400000, "wellnessDescription": null, "highlyActiveSeconds": 2765, "activeSeconds": 6655, "sedentarySeconds": 76980, "sleepingSeconds": 0, "includesWellnessData": true, "includesActivityData": false, "includesCalorieConsumedData": false, "privacyProtected": false, "moderateIntensityMinutes": 0, "vigorousIntensityMinutes": 0, "floorsAscendedInMeters": null, "floorsDescendedInMeters": null, "floorsAscended": null, "floorsDescended": null, "intensityMinutesGoal": 150, "userFloorsAscendedGoal": 10, "minHeartRate": 57, "maxHeartRate": 121, "restingHeartRate": 57, "lastSevenDaysAvgRestingHeartRate": 54, "source": "GARMIN", "averageStressLevel": 54, "maxStressLevel": 99, "stressDuration": 47460, "restStressDuration": 9660, "activityStressDuration": 28740, "uncategorizedStressDuration": 420, "totalStressDuration": 86280, "lowStressDuration": 15000, "mediumStressDuration": 21840, "highStressDuration": 10620, "stressPercentage": 55.01, "restStressPercentage": 11.2, "activityStressPercentage": 33.31, "uncategorizedStressPercentage": 0.49, "lowStressPercentage": 17.39, "mediumStressPercentage": 25.31, "highStressPercentage": 12.31, "stressQualifier": "STRESSFUL_AWAKE", "measurableAwakeDuration": 85860, "measurableAsleepDuration": 0, "lastSyncTimestampGMT": null, "minAvgHeartRate": 59, "maxAvgHeartRate": 121, "bodyBatteryChargedValue": 2, "bodyBatteryDrainedValue": 78, "bodyBatteryHighestValue": 83, "bodyBatteryLowestValue": 5, "bodyBatteryMostRecentValue": 7, "bodyBatteryDuringSleep": null, "bodyBatteryAtWakeTime": null, "bodyBatteryVersion": 2.0, "abnormalHeartRateAlertsCount": null, "averageSpo2": 93.0, "lowestSpo2": 86, "latestSpo2": 93, "latestSpo2ReadingTimeGmt": "2024-12-31T05:00:00.0", "latestSpo2ReadingTimeLocal": "2024-12-31T00:00:00.0", "averageMonitoringEnvironmentAltitude": null, "restingCaloriesFromActivity": null, "avgWakingRespirationValue": 14.0, "highestRespirationValue": 20.0, "lowestRespirationValue": 11.0, "latestRespirationValue": 19.0, "latestRespirationTimeGMT": "2024-12-31T05:00:00.0", "respirationAlgorithmVersion": 100}