{"userProfileId": 100909212, "totalKilocalories": 3337.0, "activeKilocalories": 1102.0, "bmrKilocalories": 2235.0, "wellnessKilocalories": 3337.0, "burnedKilocalories": null, "consumedKilocalories": null, "remainingKilocalories": 3337.0, "totalSteps": 7040, "netCalorieGoal": null, "totalDistanceMeters": 5731, "wellnessDistanceMeters": 5731, "wellnessActiveKilocalories": 1102.0, "netRemainingKilocalories": 1102.0, "userDailySummaryId": 100909212, "calendarDate": "2024-07-19", "rule": {"typeId": 2, "typeKey": "private"}, "uuid": "11ec74a4e0db417a9417f0b2db985c04", "dailyStepGoal": 6930, "wellnessStartTimeGmt": "2024-07-19T06:00:00.0", "wellnessStartTimeLocal": "2024-07-19T00:00:00.0", "wellnessEndTimeGmt": "2024-07-20T06:00:00.0", "wellnessEndTimeLocal": "2024-07-20T00:00:00.0", "durationInMilliseconds": 86400000, "wellnessDescription": null, "highlyActiveSeconds": 3420, "activeSeconds": 9010, "sedentarySeconds": 48770, "sleepingSeconds": 25200, "includesWellnessData": true, "includesActivityData": false, "includesCalorieConsumedData": false, "privacyProtected": false, "moderateIntensityMinutes": 0, "vigorousIntensityMinutes": 0, "floorsAscendedInMeters": null, "floorsDescendedInMeters": null, "floorsAscended": null, "floorsDescended": null, "intensityMinutesGoal": 150, "userFloorsAscendedGoal": 10, "minHeartRate": 51, "maxHeartRate": 126, "restingHeartRate": 56, "lastSevenDaysAvgRestingHeartRate": 56, "source": "GARMIN", "averageStressLevel": 54, "maxStressLevel": 99, "stressDuration": 50760, "restStressDuration": 21540, "activityStressDuration": 12840, "uncategorizedStressDuration": 900, "totalStressDuration": 86040, "lowStressDuration": 12960, "mediumStressDuration": 12240, "highStressDuration": 25560, "stressPercentage": 59.0, "restStressPercentage": 25.03, "activityStressPercentage": 14.92, "uncategorizedStressPercentage": 1.05, "lowStressPercentage": 15.06, "mediumStressPercentage": 14.23, "highStressPercentage": 29.71, "stressQualifier": "STRESSFUL", "measurableAwakeDuration": 62040, "measurableAsleepDuration": 23100, "lastSyncTimestampGMT": null, "minAvgHeartRate": 54, "maxAvgHeartRate": 124, "bodyBatteryChargedValue": 51, "bodyBatteryDrainedValue": 60, "bodyBatteryHighestValue": 65, "bodyBatteryLowestValue": 5, "bodyBatteryMostRecentValue": 5, "bodyBatteryDuringSleep": 50, "bodyBatteryAtWakeTime": null, "bodyBatteryVersion": 2.0, "abnormalHeartRateAlertsCount": null, "averageSpo2": 91.0, "lowestSpo2": 81, "latestSpo2": 91, "latestSpo2ReadingTimeGmt": "2024-07-20T05:58:00.0", "latestSpo2ReadingTimeLocal": "2024-07-19T23:58:00.0", "averageMonitoringEnvironmentAltitude": null, "restingCaloriesFromActivity": null, "avgWakingRespirationValue": 13.0, "highestRespirationValue": 20.0, "lowestRespirationValue": 9.0, "latestRespirationValue": 13.0, "latestRespirationTimeGMT": "2024-07-20T06:00:00.0"}