{"userProfileId": 100909212, "totalKilocalories": 2864.0, "activeKilocalories": 629.0, "bmrKilocalories": 2235.0, "wellnessKilocalories": 2864.0, "burnedKilocalories": null, "consumedKilocalories": null, "remainingKilocalories": 2864.0, "totalSteps": 7242, "netCalorieGoal": null, "totalDistanceMeters": 6726, "wellnessDistanceMeters": 6726, "wellnessActiveKilocalories": 629.0, "netRemainingKilocalories": 629.0, "userDailySummaryId": 100909212, "calendarDate": "2024-04-22", "rule": {"typeId": 2, "typeKey": "private"}, "uuid": "16de0b245620484fac2357095c23c119", "dailyStepGoal": 6810, "wellnessStartTimeGmt": "2024-04-22T04:00:00.0", "wellnessStartTimeLocal": "2024-04-22T00:00:00.0", "wellnessEndTimeGmt": "2024-04-23T04:00:00.0", "wellnessEndTimeLocal": "2024-04-23T00:00:00.0", "durationInMilliseconds": 86400000, "wellnessDescription": null, "highlyActiveSeconds": 3290, "activeSeconds": 6192, "sedentarySeconds": 55378, "sleepingSeconds": 21540, "includesWellnessData": true, "includesActivityData": false, "includesCalorieConsumedData": false, "privacyProtected": false, "moderateIntensityMinutes": 0, "vigorousIntensityMinutes": 15, "floorsAscendedInMeters": null, "floorsDescendedInMeters": null, "floorsAscended": null, "floorsDescended": null, "intensityMinutesGoal": 150, "userFloorsAscendedGoal": 10, "minHeartRate": 52, "maxHeartRate": 132, "restingHeartRate": 55, "lastSevenDaysAvgRestingHeartRate": 53, "source": "GARMIN", "averageStressLevel": 49, "maxStressLevel": 99, "stressDuration": 49200, "restStressDuration": 23820, "activityStressDuration": 11880, "uncategorizedStressDuration": 1440, "totalStressDuration": 86340, "lowStressDuration": 14700, "mediumStressDuration": 14700, "highStressDuration": 19800, "stressPercentage": 56.98, "restStressPercentage": 27.59, "activityStressPercentage": 13.76, "uncategorizedStressPercentage": 1.67, "lowStressPercentage": 17.03, "mediumStressPercentage": 17.03, "highStressPercentage": 22.93, "stressQualifier": "STRESSFUL", "measurableAwakeDuration": 63180, "measurableAsleepDuration": 21720, "lastSyncTimestampGMT": null, "minAvgHeartRate": 53, "maxAvgHeartRate": 130, "bodyBatteryChargedValue": 51, "bodyBatteryDrainedValue": 69, "bodyBatteryHighestValue": 74, "bodyBatteryLowestValue": 5, "bodyBatteryMostRecentValue": 5, "bodyBatteryDuringSleep": null, "bodyBatteryAtWakeTime": null, "bodyBatteryVersion": 2.0, "abnormalHeartRateAlertsCount": null, "averageSpo2": 92.0, "lowestSpo2": 87, "latestSpo2": 93, "latestSpo2ReadingTimeGmt": "2024-04-23T04:00:00.0", "latestSpo2ReadingTimeLocal": "2024-04-23T00:00:00.0", "averageMonitoringEnvironmentAltitude": null, "restingCaloriesFromActivity": null, "avgWakingRespirationValue": 14.0, "highestRespirationValue": 21.0, "lowestRespirationValue": 8.0, "latestRespirationValue": 16.0, "latestRespirationTimeGMT": "2024-04-23T04:00:00.0"}