{"userProfileId": 100909212, "totalKilocalories": 2408.0, "activeKilocalories": 84.0, "bmrKilocalories": 2324.0, "wellnessKilocalories": 2408.0, "burnedKilocalories": null, "consumedKilocalories": null, "remainingKilocalories": 2408.0, "totalSteps": 1475, "netCalorieGoal": null, "totalDistanceMeters": 1208, "wellnessDistanceMeters": 1208, "wellnessActiveKilocalories": 84.0, "netRemainingKilocalories": 84.0, "userDailySummaryId": 100909212, "calendarDate": "2024-11-08", "rule": {"typeId": 2, "typeKey": "private"}, "uuid": "95aa6367d6894a5199c39d60557a3263", "dailyStepGoal": 7200, "wellnessStartTimeGmt": "2024-11-08T05:00:00.0", "wellnessStartTimeLocal": "2024-11-08T00:00:00.0", "wellnessEndTimeGmt": "2024-11-09T05:00:00.0", "wellnessEndTimeLocal": "2024-11-09T00:00:00.0", "durationInMilliseconds": 86400000, "wellnessDescription": null, "highlyActiveSeconds": 585, "activeSeconds": 1588, "sedentarySeconds": 51407, "sleepingSeconds": 32820, "includesWellnessData": true, "includesActivityData": false, "includesCalorieConsumedData": false, "privacyProtected": false, "moderateIntensityMinutes": 0, "vigorousIntensityMinutes": 0, "floorsAscendedInMeters": null, "floorsDescendedInMeters": null, "floorsAscended": null, "floorsDescended": null, "intensityMinutesGoal": 150, "userFloorsAscendedGoal": 10, "minHeartRate": 48, "maxHeartRate": 108, "restingHeartRate": 57, "lastSevenDaysAvgRestingHeartRate": 54, "source": "GARMIN", "averageStressLevel": 40, "maxStressLevel": 95, "stressDuration": 49560, "restStressDuration": 32580, "activityStressDuration": 3300, "uncategorizedStressDuration": 720, "totalStressDuration": 86160, "lowStressDuration": 21000, "mediumStressDuration": 19200, "highStressDuration": 9360, "stressPercentage": 57.52, "restStressPercentage": 37.81, "activityStressPercentage": 3.83, "uncategorizedStressPercentage": 0.84, "lowStressPercentage": 24.37, "mediumStressPercentage": 22.28, "highStressPercentage": 10.86, "stressQualifier": "STRESSFUL", "measurableAwakeDuration": 52860, "measurableAsleepDuration": 32580, "lastSyncTimestampGMT": null, "minAvgHeartRate": 50, "maxAvgHeartRate": 105, "bodyBatteryChargedValue": 62, "bodyBatteryDrainedValue": 59, "bodyBatteryHighestValue": 65, "bodyBatteryLowestValue": 5, "bodyBatteryMostRecentValue": 8, "bodyBatteryDuringSleep": 60, "bodyBatteryAtWakeTime": 65, "bodyBatteryVersion": 2.0, "abnormalHeartRateAlertsCount": null, "averageSpo2": 90.0, "lowestSpo2": 84, "latestSpo2": 89, "latestSpo2ReadingTimeGmt": "2024-11-09T04:43:00.0", "latestSpo2ReadingTimeLocal": "2024-11-08T23:43:00.0", "averageMonitoringEnvironmentAltitude": null, "restingCaloriesFromActivity": null, "avgWakingRespirationValue": 13.0, "highestRespirationValue": 17.0, "lowestRespirationValue": 8.0, "latestRespirationValue": 14.0, "latestRespirationTimeGMT": "2024-11-09T05:00:00.0", "respirationAlgorithmVersion": 100}